LICENSE
MANIFEST.in
README.md
setup.cfg
setup.py
batching/__init__.py
batching/builder.py
batching/generator.py
batching/storage.py
batching/storage_meta.py
batching/translate.py
batching.egg-info/PKG-INFO
batching.egg-info/SOURCES.txt
batching.egg-info/dependency_links.txt
batching.egg-info/not-zip-safe
batching.egg-info/requires.txt
batching.egg-info/top_level.txt