Metadata-Version: 2.1
Name: batching
Version: 1.1.1
Summary: Batching is a set of tools to format data for training sequence models
Home-page: https://github.com/cirick/batching
Author: Charles Irick
Author-email: cirick@gmail.com
License: MIT
Download-URL: https://github.com/cirick/batching/archive/v1.0.8.tar.gz
Platform: UNKNOWN
License-File: LICENSE
